{
    "date": "2024-07-05",
    "my_callsign": "GM5ALX/P",
    "my_locator": "IO87QE",
    "my_lat": 57.16744,
    "my_lon": -2.65245,
    "my_sota": "GM/ES-065",
    "qsos": [
        {
            "time": "114700",
            "callsign": "EA2DT",
            "band": "20m",
            "qth": "",
            "locator": "",
            "lat": null,
            "lon": null,
            "distance_km": null,
            "sota_ref": "",
            "comment": ""
        },
        {
            "time": "114600",
            "callsign": "SP6KEP",
            "band": "20m",
            "qth": "",
            "locator": "",
            "lat": null,
            "lon": null,
            "distance_km": null,
            "sota_ref": "",
            "comment": ""
        },
        {
            "time": "114400",
            "callsign": "EA2DDG",
            "band": "20m",
            "qth": "",
            "locator": "IN82XO",
            "lat": 42.583333333333336,
            "lon": -2.083333333333333,
            "distance_km": 1622,
            "sota_ref": "",
            "comment": ""
        },
        {
            "time": "114400",
            "callsign": "3Z9VI",
            "band": "20m",
            "qth": "",
            "locator": "JN99SV",
            "lat": 49.875,
            "lon": 19.5,
            "distance_km": 1663,
            "sota_ref": "",
            "comment": ""
        },
        {
            "time": "114200",
            "callsign": "HB9EAJ/P",
            "band": "20m",
            "qth": "",
            "locator": "",
            "lat": 47.413,
            "lon": 7.6283,
            "distance_km": 1287,
            "sota_ref": "HB/SO-021",
            "comment": ""
        },
        {
            "time": "114200",
            "callsign": "S57S",
            "band": "20m",
            "qth": "",
            "locator": "JN76JB",
            "lat": 46.041666666666664,
            "lon": 14.75,
            "distance_km": 1715,
            "sota_ref": "",
            "comment": ""
        },
        {
            "time": "114000",
            "callsign": "EA1DHB",
            "band": "20m",
            "qth": "",
            "locator": "",
            "lat": null,
            "lon": null,
            "distance_km": null,
            "sota_ref": "",
            "comment": ""
        },
        {
            "time": "114000",
            "callsign": "2E0FEH",
            "band": "20m",
            "qth": "",
            "locator": "",
            "lat": null,
            "lon": null,
            "distance_km": null,
            "sota_ref": "",
            "comment": ""
        },
        {
            "time": "113900",
            "callsign": "OE6GND",
            "band": "20m",
            "qth": "",
            "locator": "JN76SR",
            "lat": 46.708333333333336,
            "lon": 15.5,
            "distance_km": 1693,
            "sota_ref": "",
            "comment": ""
        },
        {
            "time": "113900",
            "callsign": "SQ9MDF",
            "band": "20m",
            "qth": "",
            "locator": "",
            "lat": null,
            "lon": null,
            "distance_km": null,
            "sota_ref": "",
            "comment": ""
        },
        {
            "time": "113200",
            "callsign": "OK1FRN/P",
            "band": "20m",
            "qth": "",
            "locator": "",
            "lat": null,
            "lon": null,
            "distance_km": null,
            "sota_ref": "",
            "comment": ""
        },
        {
            "time": "112600",
            "callsign": "MM7RVC/P",
            "band": "20m",
            "qth": "",
            "locator": "",
            "lat": 57.01796,
            "lon": -2.359621,
            "distance_km": 24,
            "sota_ref": "GM/ES-080",
            "comment": ""
        },
        {
            "time": "112000",
            "callsign": "MM7RVC/P",
            "band": "40m",
            "qth": "",
            "locator": "",
            "lat": 57.01796,
            "lon": -2.359621,
            "distance_km": 24,
            "sota_ref": "GM/ES-080",
            "comment": ""
        },
        {
            "time": "110800",
            "callsign": "2M0WNA",
            "band": "70cm",
            "qth": "",
            "locator": "",
            "lat": null,
            "lon": null,
            "distance_km": null,
            "sota_ref": "",
            "comment": ""
        },
        {
            "time": "110400",
            "callsign": "MS0SCZ",
            "band": "70cm",
            "qth": "",
            "locator": "",
            "lat": null,
            "lon": null,
            "distance_km": null,
            "sota_ref": "",
            "comment": ""
        },
        {
            "time": "110200",
            "callsign": "GM4JXP",
            "band": "70cm",
            "qth": "",
            "locator": "",
            "lat": null,
            "lon": null,
            "distance_km": null,
            "sota_ref": "",
            "comment": ""
        },
        {
            "time": "105000",
            "callsign": "MM0RFN",
            "band": "2m",
            "qth": "",
            "locator": "IO87WE",
            "lat": 57.166666666666664,
            "lon": -2.166666666666667,
            "distance_km": 29,
            "sota_ref": "",
            "comment": ""
        },
        {
            "time": "104900",
            "callsign": "GM4JXP",
            "band": "2m",
            "qth": "",
            "locator": "",
            "lat": null,
            "lon": null,
            "distance_km": null,
            "sota_ref": "",
            "comment": ""
        },
        {
            "time": "104700",
            "callsign": "2M0WNA",
            "band": "2m",
            "qth": "",
            "locator": "",
            "lat": null,
            "lon": null,
            "distance_km": null,
            "sota_ref": "",
            "comment": ""
        }
    ]
}